jaxdpopt/data.py
jaxdpopt/dp_accounting_utils.py
jaxdpopt/jax_mask_efficient.py
jaxdpopt/models.py
jaxdpopt/examples/example.ipynb
jaxdpopt/examples/example_distributed.ipynb
jaxdpopt/examples/example_fixed_bs.ipynb
jaxdpopt-0.0.1.dist-info/licenses/LICENSE
jaxdpopt-0.0.1.dist-info/METADATA
jaxdpopt-0.0.1.dist-info/WHEEL
jaxdpopt-0.0.1.dist-info/top_level.txt
jaxdpopt-0.0.1.dist-info/RECORD
