Metadata-Version: 2.4
Name: jaxdpopt
Version: 0.0.1
Summary: Efficient DP optimization in JAX
Author-email: Sebastian Rodriguez <sebastian.rodriguez@helsinki.fi>, Marlon Tobaben <marlon.tobaben@helsinki.fi>
License:                                  Apache License
Project-URL: Homepage, https://github.com/DPBayes/Towards-Efficient-Scalable-Training-DP-DL
Keywords: differential privacy,jax,DPSGD
Requires-Python: >=3.10
License-File: LICENSE
Requires-Dist: jax>=0.4.30
Requires-Dist: flax>=0.10.0
Requires-Dist: transformers>=4.45.1
Requires-Dist: datasets>=3.0.0
Requires-Dist: dp-accounting>=0.4.4
Requires-Dist: pillow>=10.0.0
Requires-Dist: ipykernel
Provides-Extra: dev
Requires-Dist: pytest; extra == "dev"
Dynamic: license-file
